MANIFEST.in
README.txt
setup.py
helloworld/__init__.py
helloworld/hello.py
helloworld/images/__init__.py
helloworld/images/hello.gif
helloworld2019.egg-info/PKG-INFO
helloworld2019.egg-info/SOURCES.txt
helloworld2019.egg-info/dependency_links.txt
helloworld2019.egg-info/top_level.txt