Metadata-Version: 1.0
Name: helloworld2019
Version: 0.1
Summary: Hello World testing setuptools
Home-page: UNKNOWN
Author: marksandeep
Author-email: sandeep.signature@gmail.com
License: BSD
Platform: UNKNOWN
